histutils/__init__.py
histutils/camclass.py
histutils/cp_parents.py
histutils/diric.py
histutils/findnearest.py
histutils/get1Dcut.py
histutils/hstxmlparse.py
histutils/nans.py
histutils/plots.py
histutils/plotsimul.py
histutils/rawDMCreader.py
histutils/simulFrame.py
histutils/timedmc.py
histutils-0.9.2.data/scripts/ConvertDMC2h5.py
histutils-0.9.2.data/scripts/HDDcost.py
histutils-0.9.2.data/scripts/Playh5.py
histutils-0.9.2.data/scripts/RunSimulFrame.py
histutils-0.9.2.data/scripts/WhenEnd.py
histutils-0.9.2.data/scripts/WienerAurora.py
histutils-0.9.2.data/scripts/date2doy.py
histutils-0.9.2.dist-info/METADATA
histutils-0.9.2.dist-info/RECORD
histutils-0.9.2.dist-info/WHEEL
histutils-0.9.2.dist-info/top_level.txt
