Metadata-Version: 2.1
Name: histutils
Version: 0.9.2
Summary: Utilities for reading HiST data, etc.
Home-page: https://github.com/scivision/histutils
Author: Michael Hirsch, Ph.D.
License: UNKNOWN
Platform: UNKNOWN
Classifier: Intended Audience :: Science/Research
Classifier: Development Status :: 3 - Alpha
Classifier: License :: OSI Approved :: MIT License
Classifier: Topic :: Scientific/Engineering :: Atmospheric Science
Classifier: Programming Language :: Python :: 3.6
Requires-Python: >=3.6
Provides-Extra: io
Provides-Extra: plot
Provides-Extra: tests
Requires-Dist: python-dateutil
Requires-Dist: pytz
Requires-Dist: numpy
Requires-Dist: scipy
Requires-Dist: h5py
Requires-Dist: astropy
Requires-Dist: pymap3d
Requires-Dist: sciencedates
Provides-Extra: io
Requires-Dist: dascutils; extra == 'io'
Requires-Dist: themisasi; extra == 'io'
Provides-Extra: plot
Requires-Dist: tifffile; extra == 'plot'
Requires-Dist: matplotlib; extra == 'plot'
Requires-Dist: seaborn; extra == 'plot'
Provides-Extra: tests
Requires-Dist: pytest; extra == 'tests'
Requires-Dist: coveralls; extra == 'tests'
Requires-Dist: flake8; extra == 'tests'
Requires-Dist: mypy; extra == 'tests'
